gui_utilities/gui_utilities.py
gui_utilities/icons/focused_hide_text_icon.png
gui_utilities/icons/focused_show_text_icon.png
gui_utilities/icons/hide_text_icon.png
gui_utilities/icons/show_text_icon.png
gui_utilities/tlds/tlds_list.txt
gui_utilities-1.5.57.dist-info/licenses/LICENSE
gui_utilities-1.5.57.dist-info/METADATA
gui_utilities-1.5.57.dist-info/WHEEL
gui_utilities-1.5.57.dist-info/top_level.txt
gui_utilities-1.5.57.dist-info/RECORD
