Metadata-Version: 2.4
Name: gui_utilities
Version: 1.5.57
Summary: Librería de utilidades gráficas en PyQt6
Author-email: Guido Iván Gross <grossguidoivan@gmail.com>
Requires-Python: >=3.8
License-File: LICENSE
Requires-Dist: PyQt6
Dynamic: license-file
